MANIFEST.in
README.md
VERSION
requirements.txt
setup.cfg
setup.py
rhasspy_homeassistant_hermes.egg-info/PKG-INFO
rhasspy_homeassistant_hermes.egg-info/SOURCES.txt
rhasspy_homeassistant_hermes.egg-info/dependency_links.txt
rhasspy_homeassistant_hermes.egg-info/entry_points.txt
rhasspy_homeassistant_hermes.egg-info/requires.txt
rhasspy_homeassistant_hermes.egg-info/top_level.txt
rhasspyhomeassistant_hermes/__init__.py
rhasspyhomeassistant_hermes/__main__.py
tests/__init__.py